anatomize/__init__.py
anatomize/cli.py
anatomize/config.py
anatomize/py.typed
anatomize/validation.py
anatomize/version.py
anatomize/core/__init__.py
anatomize/core/discovery.py
anatomize/core/exclude.py
anatomize/core/extractor.py
anatomize/core/parser.py
anatomize/core/policy.py
anatomize/core/types.py
anatomize/formats/__init__.py
anatomize/formats/json_fmt.py
anatomize/formats/markdown_fmt.py
anatomize/formats/payloads.py
anatomize/formats/yaml_fmt.py
anatomize/generators/__init__.py
anatomize/generators/main.py
anatomize/pack/__init__.py
anatomize/pack/compress.py
anatomize/pack/deps.py
anatomize/pack/discovery.py
anatomize/pack/formats.py
anatomize/pack/ignore.py
anatomize/pack/jsonl.py
anatomize/pack/limit.py
anatomize/pack/match.py
anatomize/pack/mode.py
anatomize/pack/overview.py
anatomize/pack/pyright_lsp.py
anatomize/pack/representations.py
anatomize/pack/runner.py
anatomize/pack/slicing.py
anatomize/pack/summaries.py
anatomize/pack/tokens.py
anatomize/pack/tree.py
anatomize/pack/uses.py
anatomize/schemas/__init__.py
anatomize/schemas/hierarchy.schema.json
anatomize/schemas/module.schema.json
anatomize-0.2.1.dist-info/METADATA
anatomize-0.2.1.dist-info/WHEEL
anatomize-0.2.1.dist-info/entry_points.txt
anatomize-0.2.1.dist-info/licenses/LICENSE
anatomize-0.2.1.dist-info/RECORD
