Metadata-Version: 2.4
Name: anatomize
Version: 0.2.1
Summary: Deterministic, token-efficient codebase packs and skeleton maps for AI review (Python)
Project-URL: Homepage, https://github.com/BradSegal/anatomize
Project-URL: Documentation, https://github.com/BradSegal/anatomize#readme
Project-URL: Repository, https://github.com/BradSegal/anatomize
Author-email: Bradley Max Segal <bradleymaxsegal@gmail.com>
License-Expression: MIT
License-File: LICENSE
Keywords: ai,ast,bundle,code-analysis,llm,pack,skeleton,tree-sitter
Classifier: Development Status :: 3 - Alpha
Classifier: Intended Audience :: Developers
Classifier: License :: OSI Approved :: MIT License
Classifier: Programming Language :: Python :: 3
Classifier: Programming Language :: Python :: 3.10
Classifier: Programming Language :: Python :: 3.11
Classifier: Programming Language :: Python :: 3.12
Classifier: Topic :: Software Development :: Code Generators
Classifier: Topic :: Software Development :: Libraries :: Python Modules
Requires-Python: >=3.10
Requires-Dist: pydantic>=2.0
Requires-Dist: pyyaml>=6.0
Requires-Dist: tiktoken>=0.5
Requires-Dist: tomli>=2.0
Requires-Dist: tree-sitter-python<0.22,>=0.21
Requires-Dist: tree-sitter<0.22,>=0.21
Requires-Dist: typer>=0.9
Provides-Extra: dev
Requires-Dist: black>=23.0; extra == 'dev'
Requires-Dist: build; extra == 'dev'
Requires-Dist: mypy>=1.0; extra == 'dev'
Requires-Dist: pytest-cov>=4.0; extra == 'dev'
Requires-Dist: pytest>=7.0; extra == 'dev'
Requires-Dist: ruff>=0.1; extra == 'dev'
Requires-Dist: twine; extra == 'dev'
Requires-Dist: types-pyyaml; extra == 'dev'
